Workbook
Name AllAmount: Table1[[#All],[Amount ]]
Name AllAmounts: Table1[[#Headers],[Amount ]]
Name Slicer_Month: #N/A
Name Slicer_Month1: #N/A

Sheet student_budget_practice
A1: Date | B1: Category | C1: Subcategory | D1: Description | E1: Amount | F1: Payment Method | G1: Expense Type | H1: Month
A2: 45312 | B2: Shopping | C2: Personal Care | D2: Nykaa skincare order | E2: 1097.9 | F2: UPI | G2: Need | H2: January
A3: 45295 | B3: Miscellaneous | C3: Travel | D3: Train ticket home | E3: 3888.11 | F3: UPI | G3: Want | H3: January
A4: 45292 | B4: Transportation | C4: Fuel | D4: Fuel refill bike | E4: 104.41 | F4: Cash | G4: Need | H4: January
A5: 45315 | B5: Food | C5: Meal Prep | D5: Protein powder top-up | E5: 406.23 | F5: UPI | G5: Need | H5: January
A6: 45300 | B6: Healthcare | C6: Mental Health | D6: Counselling session | E6: 162.95 | F6: UPI | G6: Need | H6: January
A7: 45299 | B7: Transportation | C7: Vehicle Maintenance | D7: Bike service TVS | E7: 587.12 | F7: Debit Card | G7: Need | H7: January
A8: 45299 | B8: Education | C8: Books & Stationery | D8: Printer paper | E8: 2843.2 | F8: Credit Card | G8: Need | H8: January
A9: 45296 | B9: Shopping | C9: Gifts | D9: Farewell gift pooling | E9: 3378.83 | F9: UPI | G9: Want | H9: January
A10: 45315 | B10: Shopping | C10: Home Essentials | D10: Extension cord | E10: 1589.54 | F10: Cash | G10: Need | H10: January
A11: 45295 | B11: Transportation | C11: Ride Share | D11: Rapido bike ride | E11: 52.46 | F11: Cash | G11: Want | H11: January
A12: 45313 | B12: Entertainment | C12: Hobbies | D12: Cricket bat purchase | E12: 60.43 | F12: Credit Card | G12: Want | H12: January
A13: 45315 | B13: Entertainment | C13: Movies | D13: PVR Cinemas Avengers | E13: 1296.47 | F13: Credit Card | G13: Want | H13: January
... A201: 45458 | B201: Entertainment | C201: Hobbies | D201: Guitar strings | E201: 703.25 | F201: Cash | G201: Want | H201: April

Sheet Practice_Question_Answers
C3: S.NO | D3: Questions | E3: Answers
C4: 1 | D4: What is the average transaction amount across all 200 records? | E4: =AVERAGE(Table1[[Amount ]]) -> 1477.2452
C5: 2 | D5: What is the lowest single expense recorded in the dataset? | E5: =MIN(Table1[[Amount ]]) -> 29.64
C6: 3 | D6: What is the highest single expense recorded in the dataset? | E6: =MAX(student_budget_practice!E2:E201) -> 5667.9
C7: 4 | D7: Find the median transaction amount. How does it compare to the average? | E7: =MEDIAN(Table1[[Amount ]]) -> 1110.625
C8: 5 | D8: How many transactions are classified as 'Need' expense type? | E8: =COUNTIF(Table1[Expense Type],"Need") -> 131
C9: 6 | D9: What is the total amount spent on 'Food' category? | E9: =SUMIF(Table1[Category],"Food",Table1[[Amount ]]) -> 6060.6
C10: 7 | D10: Apply a color scale (green-yellow-red) on the Amount column to visually rank spending. | E10: Done
C11: 8 | D11: Add a dropdown list in column F restricting entries to: Cash, UPI, Credit Card, Debit Card. | E11: Done
C12: 9 | D12: Create a Named Range called 'AllAmounts' for the Amount column. | E12: =AVERAGE(AllAmount) -> 1477.2452
C13: 10 | D13: Calculate the standard deviation of all transaction amounts. | E13: =STDEV(AllAmount) -> 1329.6745
C14: 11 | D14: Using the Lookup Tables sheet, look up the Budget Limit for 'Entertainment'. | E14: =VLOOKUP(Q21_Lookup_Table!A6,Q21_Lookup_Table!A1:C10,2,) -> 1500
C15: 12 | D15: For each transaction row, pull the Type (Essential/Discretionary/Variable) from the CategoryTable. | E15: Type pulled for all rows using VLOOKUP
C16: 13 | D16: Transpose the monthly totals into a horizontal table and use HLOOKUP to retrieve May's total. | E16: =_xlfn.XLOOKUP('Q13'!F4,'Q13'!A4:H4,'Q13'!A5:H5,0,0,1) -> 52283.01
C17: 14 | D17: Return the Description of the most expensive transaction. | E17: =INDEX(Table1[Description],MATCH(MAX(Table1[[Amount ]]),Table1[[Amount ]],0)) -> PG accommodation fee
C18: 15 | D18: Find the Payment Method used for the minimum spend transaction. | E18: =INDEX(Table1[Payment Method],MATCH(MIN(Table1[[Amount ]]),Table1[[Amount ]],0)) -> Debit Card
C19: 16 | D19: Build a Pivot Table: Rows = Category, Values = Sum of Amount. Which category had the highest total? | E19: Done
C20: 17 | D20: Create a Pivot Table showing count of transactions per Payment Method per Month. | E20: Done
C21: 18 | D21: What is the average amount for 'Want' expenses only? | E21: =AVERAGEIF(Table1[Expense Type],"Want",Table1[[Amount ]]) -> 1410.6286
C22: 19 | D22: Which Amount bucket is most common? Use MODE on amounts rounded to nearest 100. | E22: {=MODE(ROUND(Table1[[Amount ]],-2))} -> 100
C23: 20 | D23: Highlight all 'Want' expense rows in column G with a light orange background using a formula rule. | E23: Done
C24: 21 | D24: Build a dynamic lookup: given a Category input cell, return the total spend AND the budget limit, then compute overspend/underspend. Show the formula chain. | E24: Done
C25: 22 | D25: Identify all transactions that are more than 2 standard deviations above the mean. List the count and total value of these outlier transactions | E25: Done
C26: 23 | D26: From your Category Pivot Table, insert a clustered bar chart. Add data labels, a title 'Spending by Category Jan–Jun 2024', and format the Y-axis in ₹. | E26: Done
C27: 24 | D27: Apply icon sets (red/yellow/green arrows) on the Amount column relative to the overall AVERAGE. Amounts below average = red, near = yellow, above = green. | E27: =AVERAGE(student_budget_practice!E2:E201) -> 1477.2452 | F27: Done Q24
C28: 25 | D28: Using the Named Range 'BudgetData', write an INDEX-MATCH that retrieves the month with the highest spending. Hint: =INDEX('Budget Data'!H2:H201, MATCH(MAX('Summary & Stats'!F51:F56),'Summary & Stats'!F51:F56,0)) | E28: =INDEX('Q13'!B4:G4,MATCH(MAX('Q13'!B5:G5),'Q13'!B5:G5,0)) -> March
C29: 26 | D29: Calculate the total UPI payments made for 'Need' expenses in March only. Formula: =SUMPRODUCT(('Budget Data'!F2:F201="UPI")*('Budget Data'!G2:G201="Need")*('Budget Data'!H2:H201="March")*'Budget Data'!E2:E201) | E29: {=SUMPRODUCT((student_budget_practice!F2:F201="UPI")*(student_budget_practice!G2:G201="Need")*(student_budget_practice!H2:H201="March")*student_budget_practice!E2:E201)} -> 11327.29
C30: 27 | D30: Wrap the Budget Limit VLOOKUP in IFERROR to display 'Not Budgeted' if a category isn't in the lookup table. | E30: Done
C31: 28 | D31: Design a 3-pivot-table dashboard: (1) Monthly trend, (2) Need vs Want split, (3) Payment method breakdown. Link all three to a single Month slicer. | E31: Done
C32: 29 | D32: Calculate month-over-month % change in total spending for each of the 6 months. Identify if there is an upward or downward trend. | E32: Done
C33: 30 | D33: Using SUMIF, AVERAGEIF, COUNTIF and named ranges, build a one-page KPI block showing: Total Spend, Avg Daily Spend, Needs%, Wants%, Top Category, Most-used Payment Method. | E33: Done

Sheet Q12
D2: Q:12
D4: {=VLOOKUP(Table1[Category],Q21_Lookup_Table!A3:C10,3,)} -> Discretionary
D5: Variable
D6: Essential
D7: Essential
D8: Essential
D9: Essential
D10: Essential
D11: Discretionary
D12: Discretionary
D13: Essential
D14: Discretionary
D15: Discretionary
D16: Discretionary
... D203: Discretionary

Sheet Q13
B3: Column Labels
B4: January | C4: February | D4: March | E4: April | F4: May | G4: June | H4: Grand Total
A5: Sum of Amount | B5: 32727.32 | C5: 43336.08 | D5: 68483 | E5: 46461.67 | F5: 52283.01 | G5: 52157.96 | H5: 295449.04
A10: Answers | B10: Q:24
A13: >> Answer | B13: =INDEX(B4:G4,MATCH(MAX(B5:G5),B5:G5,0)) -> March

Sheet Q16
A3: Row Labels | B3: Sum of Amount
A4: Bills | B4: 95972.45
A5: Education | B5: 32891.28 | D5: Ans
A6: Entertainment | B6: 15289.76 | D6: =INDEX(A4:A11,MATCH(MAX(B4:B11),B4:B11,0)) -> Bills
A7: Food | B7: 6060.6
A8: Healthcare | B8: 25444.02
A9: Miscellaneous | B9: 73543.25
A10: Shopping | B10: 39483.87
A11: Transportation | B11: 6763.81
A12: Grand Total | B12: 295449.04

Sheet Q17
A3: Count of Amount | B3: Column Labels
A4: Row Labels | B4: January | C4: February | D4: March | E4: April | F4: May | G4: June | H4: Grand Total
A5: Auto-debit | C5: 1 | D5: 3 | G5: 1 | H5: 5
A6: Cash | B6: 8 | C6: 5 | D6: 5 | E6: 8 | F6: 6 | G6: 12 | H6: 44
A7: Credit Card | B7: 7 | C7: 8 | D7: 7 | E7: 6 | F7: 5 | G7: 6 | H7: 39
A8: Debit Card | B8: 7 | C8: 5 | D8: 7 | E8: 11 | F8: 12 | G8: 5 | H8: 47
A9: Net Banking | C9: 5 | D9: 4 | E9: 2 | F9: 5 | G9: 4 | H9: 20
A10: UPI | B10: 11 | C10: 9 | D10: 7 | E10: 7 | F10: 6 | G10: 5 | H10: 45
A11: Grand Total | B11: 33 | C11: 33 | D11: 33 | E11: 34 | F11: 34 | G11: 33 | H11: 200

Sheet Q21_Lookup_Table
A1: Category Reference Table
A2: Category | B2: Budget Limit (₹/month) | C2: Type
A3: Food | B3: 4000 | C3: Essential
A4: Transportation | B4: 2000 | C4: Essential
A5: Education | B5: 5000 | C5: Essential
A6: Entertainment | B6: 1500 | C6: Discretionary
A7: Shopping | B7: 3000 | C7: Discretionary
A8: Healthcare | B8: 2000 | C8: Essential
A9: Bills | B9: 8000 | C9: Essential
A10: Miscellaneous | B10: 1000 | C10: Variable
A13: Ccategory List | B13: Category Spend | C13: Budget | D13: Variance | E13: Status | F13: iferror_occurs
A14: Food | B14: {=SUMIF(student_budget_practice!B:B,A3:A10,student_budget_practice!E:E)} -> 6060.6 | C14: {=VLOOKUP(A3:A10,$A$3:$B$10,2,FALSE)*6} -> 24000 | D14: =B14-C14 -> -17939.4 | E14: =IF(D14>0,"OVER by ₹"&TEXT(D14,"#,##0.00"),"UNDER by ₹"&TEXT(ABS(D14),"#,##0.00")) -> UNDER by ₹17,939.40 | F14: =IFERROR(VLOOKUP(A15,_xlfn.ANCHORARRAY(C14),3,FALSE),"Not budgeted") -> Not budgeted
A15: Transportation | B15: 6763.81 | C15: 12000 | D15: =B15-C15 -> -5236.19 | E15: =IF(D15>0,"OVER by ₹"&TEXT(D15,"#,##0.00"),"UNDER by ₹"&TEXT(ABS(D15),"#,##0.00")) -> UNDER by ₹5,236.19 | F15: =IFERROR(VLOOKUP(A15,_xlfn.ANCHORARRAY(C15),3,FALSE),"Not budgeted") -> Not budgeted
A16: Education | B16: 32891.28 | C16: 30000 | D16: =B16-C16 -> 2891.28 | E16: =IF(D16>0,"OVER by ₹"&TEXT(D16,"#,##0.00"),"UNDER by ₹"&TEXT(ABS(D16),"#,##0.00")) -> OVER by ₹2,891.28 | F16: =IFERROR(VLOOKUP(A16,_xlfn.ANCHORARRAY(C16),3,FALSE),"Not budgeted") -> Not budgeted
A17: Entertainment | B17: 15289.76 | C17: 9000 | D17: =B17-C17 -> 6289.76 | E17: =IF(D17>0,"OVER by ₹"&TEXT(D17,"#,##0.00"),"UNDER by ₹"&TEXT(ABS(D17),"#,##0.00")) -> OVER by ₹6,289.76 | F17: =IFERROR(VLOOKUP(A17,_xlfn.ANCHORARRAY(C17),3,FALSE),"Not budgeted") -> Not budgeted
A18: Shopping | B18: 39483.87 | C18: 18000 | D18: =B18-C18 -> 21483.87 | E18: =IF(D18>0,"OVER by ₹"&TEXT(D18,"#,##0.00"),"UNDER by ₹"&TEXT(ABS(D18),"#,##0.00")) -> OVER by ₹21,483.87 | F18: =IFERROR(VLOOKUP(A18,_xlfn.ANCHORARRAY(C18),3,FALSE),"Not budgeted") -> Not budgeted
A19: Healthcare | B19: 25444.02 | C19: 12000 | D19: =B19-C19 -> 13444.02 | E19: =IF(D19>0,"OVER by ₹"&TEXT(D19,"#,##0.00"),"UNDER by ₹"&TEXT(ABS(D19),"#,##0.00")) -> OVER by ₹13,444.02 | F19: =IFERROR(VLOOKUP(A19,_xlfn.ANCHORARRAY(C19),3,FALSE),"Not budgeted") -> Not budgeted
A20: Bills | B20: 95972.45 | C20: 48000 | D20: =B20-C20 -> 47972.45 | E20: =IF(D20>0,"OVER by ₹"&TEXT(D20,"#,##0.00"),"UNDER by ₹"&TEXT(ABS(D20),"#,##0.00")) -> OVER by ₹47,972.45 | F20: =IFERROR(VLOOKUP(A20,_xlfn.ANCHORARRAY(C20),3,FALSE),"Not budgeted") -> Not budgeted
A21: Miscellaneous | B21: 73543.25 | C21: 6000 | D21: =B21-C21 -> 67543.25 | E21: =IF(D21>0,"OVER by ₹"&TEXT(D21,"#,##0.00"),"UNDER by ₹"&TEXT(ABS(D21),"#,##0.00")) -> OVER by ₹67,543.25 | F21: =IFERROR(VLOOKUP(A21,_xlfn.ANCHORARRAY(C21),3,FALSE),"Not budgeted") -> Not budgeted

Sheet Q23
A1: Row Labels | B1: Sum of Category Spend
A2: Bills | B2: 95972.45
A3: Education | B3: 32891.28
A4: Entertainment | B4: 15289.76
A5: Food | B5: 6060.6
A6: Healthcare | B6: 25444.02
A7: Miscellaneous | B7: 73543.25
A8: Shopping | B8: 39483.87
A9: Transportation | B9: 6763.81
A10: Grand Total | B10: 295449.04

Sheet Q22
F6: Threshold | G6: Outlier Count | H6: Outlier Total
F9: =AVERAGE(Table1[[Amount ]])+2*STDEV(Table1[[Amount ]]) -> 4136.5941 | G9: =COUNTIF(Table1[[Amount ]],">"&F9) -> 10 | H9: =SUMIF(Table1[[Amount ]],">"&'Q22'!F9,Table1[[Amount ]]) -> 48006.58

Sheet pivot_1
A3: Row Labels | B3: Sum of Amount
A4: March | B4: 68483
A5: Grand Total | B5: 68483

Sheet pivot_3
A3: Row Labels | B3: Count of Amount
A4: Cash | B4: 6
A5: Credit Card | B5: 5
A6: Debit Card | B6: 12
A7: Net Banking | B7: 5
A8: UPI | B8: 6
A9: Grand Total | B9: 34

Sheet pivot_2
A3: Row Labels | B3: Sum of Amount
A4: Need | B4: 40872.22
A5: Want | B5: 11410.79
A6: Grand Total | B6: 52283.01

Sheet Q29
F5: Column Labels | O5: Standard MoM formula.
F6: January | G6: February | H6: March | I6: April | J6: May | K6: June | L6: Grand Total | O6: =(G7-F7)/F7 -> 0.32415609
E7: Sum of Amount | F7: 32727.32 | G7: 43336.08 | H7: 68483 | I7: 46461.67 | J7: 52283.01 | K7: 52157.96 | L7: 295449.04 | O7: =(H7-G7)/G7 -> 0.58027676
O8: =(I7-H7)/H7 -> -0.32155907
O9: =(J7-I7)/I7 -> 0.12529339
O10: =(K7-J7)/J7 -> -0.0023917904

Sheet Q30
E5: Column1 | F5: Column2 | G5: Column3
E6: KPI | F6: Formula | G6: Value
E8: Total Spend | F8: SUM(E2:E201) | G8: =SUM(student_budget_practice!E2:E201) -> 295449.04
E9: Avg Daily Spend | F9: SUM(E2:E201)/182 | G9: =SUM(student_budget_practice!E2:E201)/182 -> 1623.3464
E10: Needs % | F10: SUMIF(G2:G201,"Need",E2:E201)/SUM(E2:E201) | G10: =SUMIF(student_budget_practice!G2:G201,"Need",student_budget_practice!E2:E201)/SUM(student_budget_practice!E2:E201) -> 0.67055784
E11: Wants % | F11: SUMIF(G2:G201,"Want",E2:E201)/SUM(E2:E201) | G11: =SUMIF(student_budget_practice!G2:G201,"Want",student_budget_practice!E2:E201)/SUM(student_budget_practice!E2:E201) -> 0.32944216
E12: Top Category | F12: INDEX(A14:A21,MATCH(MAX(B14:B21),B14:B21,0)) | G12: =INDEX(Q21_Lookup_Table!A14:A21,MATCH(MAX(Q21_Lookup_Table!B14:B21),Q21_Lookup_Table!B14:B21,0)) -> Bills
E13: Most Used Payment Method | F13: INDEX(D2:D7,MATCH(MAX(E2:E7),E2:E7,0)) | G13: =INDEX(pivot_3!A4:A8,MATCH(MAX(pivot_3!B4:B8),pivot_3!B4:B8,0)) -> Debit Card
